aligncov/__init__.py
aligncov/aligncov.py
aligncov/cli.py
aligncov-0.0.2.dist-info/AUTHORS.rst
aligncov-0.0.2.dist-info/LICENSE
aligncov-0.0.2.dist-info/METADATA
aligncov-0.0.2.dist-info/WHEEL
aligncov-0.0.2.dist-info/entry_points.txt
aligncov-0.0.2.dist-info/top_level.txt
aligncov-0.0.2.dist-info/RECORD
