Metadata-Version: 2.1
Name: aligncov
Version: 0.0.2
Summary: Obtain tidy alignment coverage info from sorted BAM files
Home-page: https://github.com/pcrxn/aligncov
Author: Liam Brown
Author-email: pcrxn@proton.me
License: MIT license
Keywords: aligncov
Classifier: Development Status :: 5 - Production/Stable
Classifier: Intended Audience :: Developers
Classifier: License :: OSI Approved :: MIT License
Classifier: Natural Language :: English
Classifier: Programming Language :: Python :: 3
Classifier: Programming Language :: Python :: 3.6
Classifier: Programming Language :: Python :: 3.7
Classifier: Programming Language :: Python :: 3.8
Requires-Python: >=3.6
License-File: LICENSE
License-File: AUTHORS.rst
Requires-Dist: pandas >=1.0.0
